setup.py
initclass_rupam/__init__.py
initclass_rupam.egg-info/PKG-INFO
initclass_rupam.egg-info/SOURCES.txt
initclass_rupam.egg-info/dependency_links.txt
initclass_rupam.egg-info/not-zip-safe
initclass_rupam.egg-info/top_level.txt