Metadata-Version: 1.0
Name: initclass-rupam
Version: 0.1
Summary: Rupam' python package
Home-page: http://www.nxnvision.com
Author: Rupam Das
Author-email: info@nxnvision.com
License: GPL
Platform: UNKNOWN
